evaScanner-1.5.2.data/scripts/niah
evaScanner-1.5.2.dist-info/DESCRIPTION.rst
evaScanner-1.5.2.dist-info/METADATA
evaScanner-1.5.2.dist-info/RECORD
evaScanner-1.5.2.dist-info/WHEEL
evaScanner-1.5.2.dist-info/metadata.json
evaScanner-1.5.2.dist-info/top_level.txt
src/__init__.py
